lnsimulator/__init__.py
lnsimulator/ln_utils.py
lnsimulator/simulator/__init__.py
lnsimulator/simulator/genetic_routing.py
lnsimulator/simulator/graph_preprocessing.py
lnsimulator/simulator/path_searching.py
lnsimulator/simulator/transaction_sampling.py
lnsimulator/simulator/transaction_simulator.py
lnsimulator-0.1.0.dist-info/LICENSE
lnsimulator-0.1.0.dist-info/METADATA
lnsimulator-0.1.0.dist-info/WHEEL
lnsimulator-0.1.0.dist-info/top_level.txt
lnsimulator-0.1.0.dist-info/RECORD
