Metadata-Version: 2.1
Name: lnsimulator
Version: 0.1.0
Summary: Traffic Simulator for Bitcoin's Lightning Network 
Home-page: https://github.com/ferencberes/LNTrafficSimulator
Author: Ferenc Beres
Author-email: fberes@info.ilab.sztaki.hu
Keywords: bitcoin,lightning-network,simulator,simulation,research,cryptoeconomics
License-File: LICENSE
Requires-Dist: pandas
Requires-Dist: numpy
Requires-Dist: networkx
Requires-Dist: matplotlib
Requires-Dist: seaborn
Requires-Dist: tqdm
